legnext/__init__.py
legnext/client.py
legnext/py.typed
legnext/webhook.py
legnext/_internal/__init__.py
legnext/_internal/http_client.py
legnext/resources/__init__.py
legnext/resources/account.py
legnext/resources/midjourney.py
legnext/resources/tasks.py
legnext/types/__init__.py
legnext/types/canvas.py
legnext/types/enums.py
legnext/types/errors.py
legnext/types/requests.py
legnext/types/responses.py
legnext/types/shared.py
legnext-0.2.4.dist-info/METADATA
legnext-0.2.4.dist-info/WHEEL
legnext-0.2.4.dist-info/licenses/LICENSE
legnext-0.2.4.dist-info/RECORD
