Metadata-Version: 2.4
Name: legnext
Version: 0.2.4
Summary: Python SDK for Legnext AI API - Professional image and video generation using Midjourney models
Project-URL: Homepage, https://legnext.ai
Project-URL: Documentation, https://legnext.ai/docs
Author-email: tobias-hui <huikai@tritonix.cn>
License: Apache-2.0
License-File: LICENSE
Keywords: ai,api-client,image-generation,legnext,midjourney,video-generation
Classifier: Development Status :: 3 - Alpha
Classifier: Intended Audience :: Developers
Classifier: License :: OSI Approved :: Apache Software License
Classifier: Programming Language :: Python :: 3
Classifier: Programming Language :: Python :: 3.10
Classifier: Programming Language :: Python :: 3.11
Classifier: Programming Language :: Python :: 3.12
Classifier: Topic :: Multimedia :: Graphics
Classifier: Topic :: Software Development :: Libraries :: Python Modules
Requires-Python: >=3.10
Requires-Dist: httpx>=0.27.0
Requires-Dist: pydantic>=2.0.0
Requires-Dist: typing-extensions>=4.5.0
Provides-Extra: dev
Requires-Dist: black>=24.0.0; extra == 'dev'
Requires-Dist: isort>=5.13.0; extra == 'dev'
Requires-Dist: mypy>=1.8.0; extra == 'dev'
Requires-Dist: pytest-asyncio>=0.23.0; extra == 'dev'
Requires-Dist: pytest-cov>=4.1.0; extra == 'dev'
Requires-Dist: pytest-mock>=3.12.0; extra == 'dev'
Requires-Dist: pytest>=8.0.0; extra == 'dev'
Requires-Dist: ruff>=0.1.0; extra == 'dev'
